NL/deploy.py
NL/hello.py
NL/test.py
nlweb-0.1.62.dist-info/licenses/LICENSE
nlweb-0.1.62.dist-info/licenses/LICENSE copy
nlweb-0.1.62.dist-info/METADATA
nlweb-0.1.62.dist-info/WHEEL
nlweb-0.1.62.dist-info/top_level.txt
nlweb-0.1.62.dist-info/RECORD
