Metadata-Version: 2.4
Name: nlweb
Version: 0.1.62
Summary: Example package for nlweb.org domain-style imports
Author-email: Jorge Fonseca <jorge.m.j.fonseca@example.com>
License: MIT
Requires-Python: >=3.8
License-File: LICENSE
License-File: LICENSE copy
Requires-Dist: ruamel.yaml<0.18,>=0.16
Dynamic: license-file
